jsonvice/__init__.py
jsonvice/jsonvice.py
jsonvice-1.0.2.dist-info/LICENSE.txt
jsonvice-1.0.2.dist-info/METADATA
jsonvice-1.0.2.dist-info/WHEEL
jsonvice-1.0.2.dist-info/entry_points.txt
jsonvice-1.0.2.dist-info/RECORD
