Metadata-Version: 2.1
Name: jsonvice
Version: 1.0.2
Summary: jsonvice minifies JSON files by trimming floating point precision.
Home-page: https://github.com/deftio/jsonvice
Keywords: json,minify,truncate floating point precision,json quanitize,quantize
Author: Manu Chatterjee
Author-email: deftio@deftio.com
Requires-Python: >=3.8,<4.0
Classifier: Environment :: Console
Classifier: Operating System :: OS Independent
Classifier: Programming Language :: Python :: 3
Classifier: Programming Language :: Python :: 3.8
Classifier: Programming Language :: Python :: 3.9
Classifier: Programming Language :: Python :: 3.10
Classifier: Programming Language :: Python :: 3.11
Classifier: Programming Language :: Python :: 3.12
Classifier: Topic :: Software Development :: Libraries
Classifier: Topic :: Software Development :: Libraries :: Python Modules
Classifier: Topic :: System :: Archiving :: Compression
Requires-Dist: coveralls (>=3.3.1,<4.0.0)
Requires-Dist: pytest (>=8.0.0,<9.0.0)
Requires-Dist: toml (>=0.10.2,<0.11.0)
Requires-Dist: tox (>=4.18.0,<5.0.0)
Project-URL: Repository, https://github.com/deftio/jsonvice
